MANIFEST.in
README.txt
setup.cfg
setup.py
annotater/__init__.py
annotater/model.py
annotater/model_test.py
annotater/store.py
annotater/store_test.py
annotater.egg-info/PKG-INFO
annotater.egg-info/SOURCES.txt
annotater.egg-info/dependency_links.txt
annotater.egg-info/not-zip-safe
annotater.egg-info/requires.txt
annotater.egg-info/top_level.txt
annotater/marginalia/__init__.py
annotater/marginalia/annotation.js
annotater/marginalia/config.js
annotater/marginalia/domutil.js
annotater/marginalia/example.css
annotater/marginalia/html-model.js
annotater/marginalia/log.js
annotater/marginalia/marginalia_test.py
annotater/marginalia/onload.js
annotater/marginalia/post-micro.js
annotater/marginalia/ranges.js
annotater/marginalia/rest-annotate.js
annotater/marginalia/smartcopy.js
annotater/marginalia/static-annotate.js
annotater/marginalia/lang/en.js
demo/demo.html
demo/demo.py
demo/demo_test.py
demo/index.html