Metadata-Version: 1.0
Name: annotater
Version: 0.2
Summary: Inline web annotation application and middleware using javascript and WSGI
Home-page: http://p.knowledgeforge.net/shakespeare/svn/annotater/
Author: Rufus Pollock (Open Knowledge Foundation)
Author-email: rufus@rufuspollock.org
License: MIT
Download-URL: http://p.knowledgeforge.net/shakespeare/svn/annotater/trunk
Keywords: annotation web javascript
Platform: UNKNOWN
Classifier: Development Status :: 3 - Alpha
Classifier: Environment :: Console
Classifier: Intended Audience :: Developers
Classifier: License :: OSI Approved :: MIT License
Classifier: Operating System :: OS Independent
Classifier: Programming Language :: Python
Classifier: Topic :: Software Development :: Libraries :: Python Modules
